quant_trade_framework/__init__.py
quant_trade_framework/btc/__init__.py
quant_trade_framework/btc/account.py
quant_trade_framework/btc/context.py
quant_trade_framework/btc/position.py
quant_trade_framework/btc/strategy.py
quant_trade_framework/common/__init__.py
quant_trade_framework/common/admin.py
quant_trade_framework/common/array_manager.py
quant_trade_framework/common/constant.py
quant_trade_framework/common/frozen_dir.py
quant_trade_framework/common/logConfig.py
quant_trade_framework/common/redisConfig.py
quant_trade_framework/core/__init__.py
quant_trade_framework/core/dataProcessTools.py
quant_trade_framework/core/exception_info.py
quant_trade_framework/core/object.py
quant_trade_framework/core/setting.py
quant_trade_framework/core/utility.py
quant_trade_framework/data/__init__.py
quant_trade_framework/data/database/__init__.py
quant_trade_framework/data/database/database.py
quant_trade_framework/data/database/database_mongo.py
quant_trade_framework/data/database/database_redis.py
quant_trade_framework/data/database/database_sql.py
quant_trade_framework/data/database/initialize.py
quant_trade_framework/data/models/__init__.py
quant_trade_framework/data/models/mysql_models.py
quant_trade_framework/gateway/__init__.py
quant_trade_framework/gateway/binance/__init__.py
quant_trade_framework/gateway/binance/base.py
quant_trade_framework/gateway/chinanext/__init__.py
quant_trade_framework/gateway/chinanext/benchmark_index.py
quant_trade_framework/gateway/general/__init__.py
quant_trade_framework/gateway/general/base.py
quant_trade_framework/gateway/jointquant/__init__.py
quant_trade_framework/gateway/jointquant/jqdata.py
quant_trade_framework/model/__init__.py
quant_trade_framework/model/indicators.py
quant_trade_framework/model/kline_data.py
quant_trade_framework/model/tick_data.py
quant_trade_framework/stock/__init__.py
quant_trade_framework/stock/account.py
quant_trade_framework/stock/context.py
quant_trade_framework/stock/order.py
quant_trade_framework-0.1.3.dist-info/LICENSE.txt
quant_trade_framework-0.1.3.dist-info/METADATA
quant_trade_framework-0.1.3.dist-info/WHEEL
quant_trade_framework-0.1.3.dist-info/top_level.txt
quant_trade_framework-0.1.3.dist-info/RECORD
