Metadata-Version: 2.1
Name: quant-trade-framework
Version: 0.1.3
Summary: Quant Trade Framwork
Home-page: https://github.com/yangchuan123/QuantTradeFramework.git
Author: chuan.yang
Author-email: chuan.yang0606@gmail.co,
License: UNKNOWN
Platform: UNKNOWN
Classifier: Programming Language :: Python :: 3
Classifier: License :: OSI Approved :: MIT License
Classifier: Operating System :: OS Independent
Requires-Python: >=3.6
Requires-Dist: pyecharts
Requires-Dist: matplotlib
Requires-Dist: peewee
Requires-Dist: pytz
Requires-Dist: requests
Requires-Dist: SQLAlchemy
Requires-Dist: pymongo
Requires-Dist: jqdatasdk
Requires-Dist: redis
Requires-Dist: numpy
Requires-Dist: pandas
Requires-Dist: dataclasses
Requires-Dist: strategies
